pydrobert_kaldi-0.6.4.dist-info/RECORD
pydrobert_kaldi-0.6.4.dist-info/LICENSE
pydrobert_kaldi-0.6.4.dist-info/COPYING_Kaldi_Project
pydrobert_kaldi-0.6.4.dist-info/WHEEL
pydrobert_kaldi-0.6.4.dist-info/entry_points.txt
pydrobert_kaldi-0.6.4.dist-info/top_level.txt
pydrobert_kaldi-0.6.4.dist-info/METADATA
pydrobert/kaldi/logging.py
pydrobert/kaldi/_version.py
pydrobert/kaldi/command_line.py
pydrobert/kaldi/__init__.py
pydrobert/kaldi/_internal.cpython-310-darwin.so
pydrobert/kaldi/feat/command_line.py
pydrobert/kaldi/feat/__init__.py
pydrobert/kaldi/io/enums.py
pydrobert/kaldi/io/util.py
pydrobert/kaldi/io/command_line.py
pydrobert/kaldi/io/__init__.py
pydrobert/kaldi/io/duck_streams.py
pydrobert/kaldi/io/argparse.py
pydrobert/kaldi/io/table_streams.py
pydrobert/kaldi/io/corpus.py
pydrobert/kaldi/eval/util.py
pydrobert/kaldi/eval/command_line.py
pydrobert/kaldi/eval/__init__.py
