Metadata-Version: 2.1
Name: pydrobert-kaldi
Version: 0.6.4
Summary: Python wrapper for Kaldi
Home-page: https://github.com/sdrobert/pydrobert-kaldi
Author: Sean Robertson
Author-email: sdrobert@cs.toronto.edu
License: Apache-2.0
Project-URL: Documentation, https://pydrobert-kaldi.readthedocs.io
Classifier: Development Status :: 3 - Alpha
Classifier: License :: OSI Approved :: Apache Software License
Classifier: Programming Language :: Python :: 3
Requires-Python: >=3.9
License-File: LICENSE
License-File: COPYING_Kaldi_Project
Requires-Dist: numpy
Provides-Extra: pytorch
Requires-Dist: torch; extra == "pytorch"
